LICENSE.txt
MANIFEST.in
README.rst
setup.py
dj_albertson/__init__.py
dj_albertson/mixins.py
dj_albertson/models.py
dj_albertson/test_settings.py
django_albertson.egg-info/PKG-INFO
django_albertson.egg-info/SOURCES.txt
django_albertson.egg-info/dependency_links.txt
django_albertson.egg-info/requires.txt
django_albertson.egg-info/top_level.txt