Metadata-Version: 1.0
Name: django-albertson
Version: 0.1.1
Summary: Integration library for Django and Albertson.
Home-page: https://github.com/FocusLab/django-albertson
Author: Sean O'Connor
Author-email: sean@focuslab.io
License: BSD
Platform: UNKNOWN
Classifier: Development Status :: 2 - Pre-Alpha
Classifier: Intended Audience :: Developers
Classifier: License :: OSI Approved :: BSD License
Classifier: Programming Language :: Python
Classifier: Topic :: Software Development :: Libraries :: Python Modules
